<?xml version="1.0" encoding="utf-8"?>
<odoo>

    <record id="view_task_form_inherited_approval" model="ir.ui.view">
        <field name="name">project.task.form.inherited.approval</field>
        <field name="model">project.task</field>
        <field name="inherit_id" ref="project.view_task_form2"/>
        <field name="arch" type="xml">
            <xpath expr="//field[@name='tag_ids']" position="after">
                <field name="approval_status" invisible="1"/>
            </xpath>

            <xpath expr="//header" position="inside">
                <button name="action_approve_task" string="Approve" type="object" class="btn-success" invisible="approval_status == '2_approved'" groups="project.group_project_manager"/>
                <button name="action_decline_task" string="Decline" type="object" class="btn-danger" invisible="approval_status == '3_declined'" groups="project.group_project_manager"/>
                <button name="action_on_hold_task" string="On Hold" type="object" class="btn-warning" invisible="approval_status == '4_on_hold'" groups="project.group_project_manager"/>
                <button name="action_reset_pending" string="Reset to Pending" type="object" invisible="approval_status == '1_pending'" groups="project.group_project_manager"/>
            </xpath>
            
            <xpath expr="//div[hasclass('oe_title')]" position="before">
                <div class="mb-2">
                    <span class="badge rounded-pill text-bg-success fs-6 py-2 px-3" invisible="approval_status != '2_approved'">
                        <i class="fa fa-check me-1"/> Approved
                    </span>
                    <span class="badge rounded-pill text-bg-danger fs-6 py-2 px-3" invisible="approval_status != '3_declined'">
                        <i class="fa fa-times me-1"/> Declined
                    </span>
                    <span class="badge rounded-pill text-bg-warning fs-6 py-2 px-3" invisible="approval_status != '4_on_hold'">
                        <i class="fa fa-pause me-1"/> On Hold
                    </span>
                </div>
            </xpath>
        </field>
    </record>

    <record id="view_task_kanban_inherited_approval" model="ir.ui.view">
        <field name="name">project.task.kanban.inherited.approval</field>
        <field name="model">project.task</field>
        <field name="inherit_id" ref="project.view_task_kanban"/>
        <field name="arch" type="xml">
            <xpath expr="//templates" position="before">
                <field name="approval_status"/>
            </xpath>
            
            <xpath expr="//templates//field[@name='tag_ids']" position="after">
                <div class="d-flex mt-2 mb-1">
                    <button name="action_approve_task" type="object" class="btn btn-sm btn-outline-success me-1 p-1" invisible="approval_status == '2_approved'" groups="project.group_project_manager" title="Approve">
                        <i class="fa fa-check"/>
                    </button>
                    <button name="action_decline_task" type="object" class="btn btn-sm btn-outline-danger me-1 p-1" invisible="approval_status == '3_declined'" groups="project.group_project_manager" title="Decline">
                        <i class="fa fa-times"/>
                    </button>
                    <button name="action_on_hold_task" type="object" class="btn btn-sm btn-outline-warning p-1" invisible="approval_status == '4_on_hold'" groups="project.group_project_manager" title="On Hold">
                        <i class="fa fa-pause"/>
                    </button>
                </div>
            </xpath>
        </field>
    </record>

    <record id="view_task_search_inherited_approval" model="ir.ui.view">
        <field name="name">project.task.search.inherited.approval</field>
        <field name="model">project.task</field>
        <field name="inherit_id" ref="project.view_task_search_form"/>
        <field name="arch" type="xml">
            <xpath expr="//filter[@name='my_tasks']" position="before">
                <filter string="Open Tasks Only" name="filter_open_tasks" domain="[('is_closed', '=', False)]"/>
                <separator/>
                <filter string="Last 7 Days" name="filter_last_7_days" domain="[('create_date', '&gt;=', (context_today() - relativedelta(days=7)).strftime('%Y-%m-%d'))]"/>
                <filter string="Last Week" name="filter_last_week" domain="[('create_date', '&gt;=', (context_today() - relativedelta(weeks=1)).strftime('%Y-%m-%d'))]"/>
                <separator/>
            </xpath>
            <xpath expr="//filter[@name='stage']" position="after">
                <filter string="Approval Status" name="group_by_approval_status" context="{'group_by': 'approval_status'}"/>
                <filter string="Creation Month" name="group_by_month" context="{'group_by': 'create_date:month'}"/>
            </xpath>
        </field>
    </record>

    <record id="action_project_task_approvals" model="ir.actions.act_window">
        <field name="name">Task Approvals</field>
        <field name="res_model">project.task</field>
        <field name="view_mode">kanban,list,form</field>
        <field name="context">{
            'search_default_filter_open_tasks': 1,
            'group_by': 'approval_status'
        }</field>
    </record>

    <menuitem id="menu_project_task_approvals" 
              name="Task Approvals" 
              action="action_project_task_approvals" 
              web_icon="project,static/description/icon.png"
              sequence="15"/>

</odoo>